bgspace/__init__.py
bgspace/core.py
bgspace/functions.py
bgspace/utils.py
bgspace-0.0.1.dist-info/LICENSE
bgspace-0.0.1.dist-info/METADATA
bgspace-0.0.1.dist-info/WHEEL
bgspace-0.0.1.dist-info/top_level.txt
bgspace-0.0.1.dist-info/RECORD
